caput/__init__.py
caput/__init__.py.orig
caput/_version.py
caput-1.1.dist-info/METADATA
caput-1.1.dist-info/WHEEL
caput-1.1.dist-info/licenses/LICENSE.md
caput-1.1.dist-info/RECORD
