Metadata-Version: 2.4
Name: caput
Version: 1.1
Summary: Manage file metadata with YAML front-matter.
Project-URL: Homepage, https://github.com/eykd/caput
Project-URL: Issues, https://github.com/eykd/caput/issues
Project-URL: Repository, https://github.com/eykd/caput
Author-email: David Eyk <david@worldsenoughstudios.com>
License-Expression: MIT
License-File: LICENSE.md
Classifier: Development Status :: 5 - Production/Stable
Classifier: Intended Audience :: Developers
Classifier: License :: OSI Approved :: BSD License
Classifier: Operating System :: OS Independent
Classifier: Programming Language :: Python :: 3
Classifier: Topic :: Software Development :: Libraries
Requires-Python: >=3.11
Requires-Dist: funcy
Requires-Dist: ruamel-yaml
